pormat/__init__.py
pormat/cli.py
pormat/config/__init__.py
pormat/config/defaults.py
pormat/config/loader.py
pormat/detector.py
pormat/formatters/__init__.py
pormat/formatters/json_formatter.py
pormat/formatters/python_formatter.py
pormat/formatters/toml_formatter.py
pormat/formatters/yaml_formatter.py
pormat/parsers/__init__.py
pormat/parsers/json_parser.py
pormat/parsers/python_parser.py
pormat/parsers/toml_parser.py
pormat/parsers/yaml_parser.py
pormat/utils/__init__.py
pormat/utils/io.py
pormat-0.1.0.dist-info/WHEEL
pormat-0.1.0.dist-info/entry_points.txt
pormat-0.1.0.dist-info/METADATA
pormat-0.1.0.dist-info/RECORD
