Metadata-Version: 2.3
Name: pormat
Version: 0.1.0
Summary: A CLI tool to format and convert data (JSON/YAML/TOML/Python) in the terminal
Requires-Dist: typer>=0.12.0
Requires-Dist: pyyaml>=6.0
Requires-Dist: tomli>=2.0
Requires-Dist: tomli-w>=1.0
Requires-Dist: python-dotenv>=1.0
Requires-Python: >=3.8
